README.md
setup.py
aios/__init__.py
aios/logic.py
aios/object.py
aios/state.py
aios.egg-info/PKG-INFO
aios.egg-info/SOURCES.txt
aios.egg-info/dependency_links.txt
aios.egg-info/top_level.txt